{
  "ComponentIndexes": {
    "cmt_Header": 9,
    "cmt_InsuranceHeader": 10,
    "cmt_loginHeader": 11,
    "Component1_1": 12
  },
  "ControlUniqueGuids": {},
  "ControlUniqueIds": {
    "# projects_DataCard1": 94,
    "# projects_DataCard2": 45,
    "Account Cost in USD_DataCard1": 104,
    "Account Cost in USD_DataCard2": 47,
    "Account Dashboard Screen": 597,
    "Account End date_DataCard1": 149,
    "Account End date_DataCard2": 57,
    "Account Name_DataCard1": 372,
    "Account Name_DataCard1_1": 487,
    "Account Name_DataCard2": 37,
    "Account Name_DataCard3": 186,
    "Account Name_DataCard4": 65,
    "Account Start date_DataCard1": 144,
    "Account Start date_DataCard2": 56,
    "Account Status_DataCard1": 169,
    "Account Status_DataCard2": 61,
    "Add a new account": 35,
    "App": 1,
    "Approval for Project": 62,
    "Attachments_DataCard2": 313,
    "Attachments_DataCard3": 179,
    "Blended rate in USD_DataCard1": 457,
    "Blended rate in USD_DataCard1_1": 572,
    "Blended rate in USD_DataCard2": 243,
    "Blended rate offshore (Per Month in USD)_DataCard1": 447,
    "Blended rate offshore (Per Month in USD)_DataCard1_1": 562,
    "Blended rate offshore (Per Month in USD)_DataCard2": 233,
    "Blended rate onsite (Per Month in USD)_DataCard1": 452,
    "Blended rate onsite (Per Month in USD)_DataCard1_1": 567,
    "Blended rate onsite (Per Month in USD)_DataCard2": 238,
    "btn_Notification": 32,
    "btn_Signin": 365,
    "Button1": 23,
    "Button2": 599,
    "Button2_1": 321,
    "Button3": 601,
    "Button3_1": 324,
    "Button4": 368,
    "Button4_1": 483,
    "Button5": 369,
    "Button5_1": 484,
    "Button6": 370,
    "Button6_1": 485,
    "cmt_Header": 27,
    "cmt_Header_1": 607,
    "cmt_Header_2": 329,
    "cmt_InsuranceHeader": 4,
    "cmt_loginHeader": 10,
    "cmt_loginHeader_1": 355,
    "Comments_DataCard1": 477,
    "Comments_DataCard1_1": 592,
    "Comments_DataCard2": 308,
    "Component1_1": 15,
    "Cost_DataCard1": 129,
    "Cost_DataCard2": 53,
    "Currency_DataCard1": 99,
    "Currency_DataCard2": 46,
    "DataCardKey1": 373,
    "DataCardKey1_1": 488,
    "DataCardKey10": 419,
    "DataCardKey10_1": 534,
    "DataCardKey100": 160,
    "DataCardKey101": 165,
    "DataCardKey102": 170,
    "DataCardKey103": 175,
    "DataCardKey104": 71,
    "DataCardKey105": 180,
    "DataCardKey11": 423,
    "DataCardKey11_1": 538,
    "DataCardKey12": 428,
    "DataCardKey12_1": 543,
    "DataCardKey13": 433,
    "DataCardKey13_1": 548,
    "DataCardKey14": 438,
    "DataCardKey14_1": 553,
    "DataCardKey15": 443,
    "DataCardKey15_1": 558,
    "DataCardKey16": 448,
    "DataCardKey16_1": 563,
    "DataCardKey17": 453,
    "DataCardKey17_1": 568,
    "DataCardKey18": 458,
    "DataCardKey18_1": 573,
    "DataCardKey2": 379,
    "DataCardKey2_1": 494,
    "DataCardKey21": 463,
    "DataCardKey21_1": 578,
    "DataCardKey22": 468,
    "DataCardKey22_1": 583,
    "DataCardKey25": 473,
    "DataCardKey25_1": 588,
    "DataCardKey3": 383,
    "DataCardKey3_1": 498,
    "DataCardKey31": 478,
    "DataCardKey31_1": 593,
    "DataCardKey4": 388,
    "DataCardKey4_1": 503,
    "DataCardKey5": 393,
    "DataCardKey5_1": 508,
    "DataCardKey56": 195,
    "DataCardKey57": 199,
    "DataCardKey58": 204,
    "DataCardKey59": 209,
    "DataCardKey6": 398,
    "DataCardKey6_1": 513,
    "DataCardKey60": 214,
    "DataCardKey61": 219,
    "DataCardKey62": 224,
    "DataCardKey63": 229,
    "DataCardKey64": 234,
    "DataCardKey65": 239,
    "DataCardKey66": 244,
    "DataCardKey67": 249,
    "DataCardKey68": 254,
    "DataCardKey69": 259,
    "DataCardKey7": 403,
    "DataCardKey7_1": 518,
    "DataCardKey70": 264,
    "DataCardKey71": 269,
    "DataCardKey72": 274,
    "DataCardKey73": 279,
    "DataCardKey74": 284,
    "DataCardKey75": 289,
    "DataCardKey76": 294,
    "DataCardKey77": 299,
    "DataCardKey78": 304,
    "DataCardKey79": 309,
    "DataCardKey8": 408,
    "DataCardKey8_1": 523,
    "DataCardKey80": 314,
    "DataCardKey82": 66,
    "DataCardKey83": 76,
    "DataCardKey84": 80,
    "DataCardKey85": 85,
    "DataCardKey86": 90,
    "DataCardKey87": 95,
    "DataCardKey88": 100,
    "DataCardKey89": 105,
    "DataCardKey9": 413,
    "DataCardKey9_1": 528,
    "DataCardKey90": 110,
    "DataCardKey91": 115,
    "DataCardKey92": 120,
    "DataCardKey93": 125,
    "DataCardKey94": 130,
    "DataCardKey95": 135,
    "DataCardKey96": 140,
    "DataCardKey97": 145,
    "DataCardKey98": 150,
    "DataCardKey99": 155,
    "DataCardValue11": 424,
    "DataCardValue11_1": 539,
    "DataCardValue12": 429,
    "DataCardValue12_1": 544,
    "DataCardValue13": 434,
    "DataCardValue13_1": 549,
    "DataCardValue14": 439,
    "DataCardValue14_1": 554,
    "DataCardValue15": 444,
    "DataCardValue15_1": 559,
    "DataCardValue16": 449,
    "DataCardValue16_1": 564,
    "DataCardValue17": 454,
    "DataCardValue17_1": 569,
    "DataCardValue18": 459,
    "DataCardValue18_1": 574,
    "DataCardValue20": 187,
    "DataCardValue21": 42,
    "DataCardValue22": 44,
    "DataCardValue25": 48,
    "DataCardValue3": 384,
    "DataCardValue3_1": 499,
    "DataCardValue31": 479,
    "DataCardValue31_1": 594,
    "DataCardValue4": 389,
    "DataCardValue4_1": 504,
    "DataCardValue5": 394,
    "DataCardValue5_1": 509,
    "DataCardValue51": 67,
    "DataCardValue53": 200,
    "DataCardValue54": 205,
    "DataCardValue55": 210,
    "DataCardValue56": 215,
    "DataCardValue57": 220,
    "DataCardValue58": 225,
    "DataCardValue59": 230,
    "DataCardValue6": 399,
    "DataCardValue6_1": 514,
    "DataCardValue60": 235,
    "DataCardValue61": 240,
    "DataCardValue62": 245,
    "DataCardValue63": 250,
    "DataCardValue64": 255,
    "DataCardValue65": 260,
    "DataCardValue66": 265,
    "DataCardValue67": 270,
    "DataCardValue68": 275,
    "DataCardValue69": 280,
    "DataCardValue7": 404,
    "DataCardValue7_1": 519,
    "DataCardValue70": 285,
    "DataCardValue71": 290,
    "DataCardValue72": 295,
    "DataCardValue73": 300,
    "DataCardValue74": 305,
    "DataCardValue75": 310,
    "DataCardValue76": 315,
    "DataCardValue77": 81,
    "DataCardValue78": 86,
    "DataCardValue79": 91,
    "DataCardValue8": 409,
    "DataCardValue8_1": 524,
    "DataCardValue80": 96,
    "DataCardValue81": 101,
    "DataCardValue82": 106,
    "DataCardValue83": 111,
    "DataCardValue84": 116,
    "DataCardValue85": 121,
    "DataCardValue86": 126,
    "DataCardValue87": 131,
    "DataCardValue88": 136,
    "DataCardValue89": 141,
    "DataCardValue9": 414,
    "DataCardValue9_1": 529,
    "DataCardValue90": 146,
    "DataCardValue91": 151,
    "DataCardValue92": 156,
    "DataCardValue93": 161,
    "DataCardValue94": 166,
    "DataCardValue95": 171,
    "DataCardValue96": 176,
    "DataCardValue97": 72,
    "DataCardValue98": 181,
    "Deepdiving Each Account Record": 63,
    "Deepdiving Each Project Record": 184,
    "Delivery Head_DataCard1": 402,
    "Delivery Head_DataCard1_1": 517,
    "Delivery Head_DataCard2": 41,
    "Delivery Head_DataCard3": 193,
    "Delivery Head_DataCard4": 84,
    "Delivery Manager_DataCard1": 397,
    "Delivery Manager_DataCard1_1": 512,
    "Delivery Manager_DataCard2": 40,
    "Delivery Manager_DataCard3": 192,
    "Delivery Manager_DataCard4": 79,
    "Dropdown1": 376,
    "Dropdown1_1": 491,
    "Dropdown2": 378,
    "Dropdown2_1": 493,
    "Dropdown3": 418,
    "Dropdown3_1": 533,
    "Dropdown4": 38,
    "Dropdown5": 464,
    "Dropdown5_1": 579,
    "Dropdown6": 469,
    "Dropdown6_1": 584,
    "Dropdown7": 474,
    "Dropdown7_1": 589,
    "Duration in yr_DataCard1": 164,
    "Duration in yr_DataCard2": 60,
    "Effort Slippage (in days)_DataCard1": 283,
    "ErrorMessage1": 374,
    "ErrorMessage1_1": 489,
    "ErrorMessage10": 420,
    "ErrorMessage10_1": 535,
    "ErrorMessage100": 162,
    "ErrorMessage101": 167,
    "ErrorMessage102": 172,
    "ErrorMessage103": 177,
    "ErrorMessage104": 73,
    "ErrorMessage105": 182,
    "ErrorMessage11": 425,
    "ErrorMessage11_1": 540,
    "ErrorMessage12": 430,
    "ErrorMessage12_1": 545,
    "ErrorMessage13": 435,
    "ErrorMessage13_1": 550,
    "ErrorMessage14": 440,
    "ErrorMessage14_1": 555,
    "ErrorMessage15": 445,
    "ErrorMessage15_1": 560,
    "ErrorMessage16": 450,
    "ErrorMessage16_1": 565,
    "ErrorMessage17": 455,
    "ErrorMessage17_1": 570,
    "ErrorMessage18": 460,
    "ErrorMessage18_1": 575,
    "ErrorMessage2": 380,
    "ErrorMessage2_1": 495,
    "ErrorMessage21": 465,
    "ErrorMessage21_1": 580,
    "ErrorMessage22": 470,
    "ErrorMessage22_1": 585,
    "ErrorMessage25": 475,
    "ErrorMessage25_1": 590,
    "ErrorMessage3": 385,
    "ErrorMessage3_1": 500,
    "ErrorMessage31": 480,
    "ErrorMessage31_1": 595,
    "ErrorMessage4": 390,
    "ErrorMessage4_1": 505,
    "ErrorMessage5": 395,
    "ErrorMessage5_1": 510,
    "ErrorMessage56": 196,
    "ErrorMessage57": 201,
    "ErrorMessage58": 206,
    "ErrorMessage59": 211,
    "ErrorMessage6": 400,
    "ErrorMessage6_1": 515,
    "ErrorMessage60": 216,
    "ErrorMessage61": 221,
    "ErrorMessage62": 226,
    "ErrorMessage63": 231,
    "ErrorMessage64": 236,
    "ErrorMessage65": 241,
    "ErrorMessage66": 246,
    "ErrorMessage67": 251,
    "ErrorMessage68": 256,
    "ErrorMessage69": 261,
    "ErrorMessage7": 405,
    "ErrorMessage7_1": 520,
    "ErrorMessage70": 266,
    "ErrorMessage71": 271,
    "ErrorMessage72": 276,
    "ErrorMessage73": 281,
    "ErrorMessage74": 286,
    "ErrorMessage75": 291,
    "ErrorMessage76": 296,
    "ErrorMessage77": 301,
    "ErrorMessage78": 306,
    "ErrorMessage79": 311,
    "ErrorMessage8": 410,
    "ErrorMessage8_1": 525,
    "ErrorMessage80": 316,
    "ErrorMessage82": 68,
    "ErrorMessage83": 77,
    "ErrorMessage84": 82,
    "ErrorMessage85": 87,
    "ErrorMessage86": 92,
    "ErrorMessage87": 97,
    "ErrorMessage88": 102,
    "ErrorMessage89": 107,
    "ErrorMessage9": 415,
    "ErrorMessage9_1": 530,
    "ErrorMessage90": 112,
    "ErrorMessage91": 117,
    "ErrorMessage92": 122,
    "ErrorMessage93": 127,
    "ErrorMessage94": 132,
    "ErrorMessage95": 137,
    "ErrorMessage96": 142,
    "ErrorMessage97": 147,
    "ErrorMessage98": 152,
    "ErrorMessage99": 157,
    "Execution Status_DataCard1": 273,
    "Form1": 371,
    "Form1_1": 486,
    "Form2": 185,
    "Form3": 64,
    "Form4": 36,
    "gal_AccountList": 618,
    "gal_AccountList_1": 341,
    "galleryTemplate3_1": 619,
    "galleryTemplate3_2": 342,
    "Geo_DataCard1": 377,
    "Geo_DataCard1_1": 492,
    "Geo_DataCard2": 188,
    "GM %_DataCard1": 442,
    "GM %_DataCard1_1": 557,
    "GM %_DataCard2": 228,
    "Gross Margin %_DataCard1": 109,
    "Gross Margin %_DataCard2": 49,
    "Group": 14,
    "grp_header": 25,
    "grp_logout": 26,
    "Host": 3,
    "ico_EyeIcon": 362,
    "ico_Notification": 33,
    "ico_Userdetailsdownarrow": 34,
    "Icon1": 19,
    "Icon2": 21,
    "Icon3": 24,
    "Image1": 18,
    "Img_CompantLogo": 6,
    "Img_CompantLogo_1": 29,
    "img_CompanyLogo": 12,
    "Img_User": 8,
    "Img_User_1": 30,
    "Label1": 17,
    "Label2": 22,
    "Label3": 598,
    "Label3_1": 319,
    "Label4": 602,
    "Label4_1": 322,
    "Label5": 605,
    "Label5_1": 325,
    "Label5_2": 328,
    "Label6": 603,
    "Label6_1": 327,
    "lbl_#Projects": 611,
    "lbl_#projects_1": 623,
    "lbl_#Projects_1": 334,
    "lbl_#projects_2": 345,
    "lbl_AccountcostinUSD": 612,
    "lbl_AccountcostinUSD_1": 625,
    "lbl_AccountcostinUSD_2": 347,
    "lbl_AccountcostinUSD_3": 335,
    "lbl_Accountname": 608,
    "lbl_Accountname_1": 624,
    "lbl_Accountname_2": 346,
    "lbl_Accountname_3": 330,
    "lbl_Blank": 617,
    "lbl_Blank_1": 340,
    "lbl_ClaimsLoginHeader": 13,
    "lbl_Cost": 615,
    "lbl_Cost_1": 628,
    "lbl_Cost_2": 350,
    "lbl_Cost_3": 338,
    "lbl_Country": 610,
    "lbl_Country_1": 620,
    "lbl_Country_2": 343,
    "lbl_Country_3": 333,
    "lbl_Don't have an account?": 366,
    "lbl_errormessage for username and password": 363,
    "lbl_Forgotpassword": 364,
    "lbl_Geo": 609,
    "lbl_Geo_1": 621,
    "lbl_Geo_2": 344,
    "lbl_Geo_3": 331,
    "lbl_Grossmargin%": 613,
    "lbl_Grossmargin%_1": 626,
    "lbl_Grossmargin%_2": 348,
    "lbl_Grossmargin%_3": 336,
    "lbl_Insurance": 7,
    "lbl_Login": 357,
    "lbl_P&L": 616,
    "lbl_P&L_1": 629,
    "lbl_P&L_2": 351,
    "lbl_P&L_3": 339,
    "lbl_Password": 360,
    "lbl_Revenue": 614,
    "lbl_Revenue_1": 627,
    "lbl_Revenue_2": 349,
    "lbl_Revenue_3": 337,
    "lbl_UserName": 9,
    "lbl_UserName_1": 31,
    "lbl-Username": 358,
    "Login": 353,
    "New Project": 367,
    "New Project_1": 482,
    "NextArrow": 622,
    "Offshore #_DataCard1": 432,
    "Offshore #_DataCard1_1": 547,
    "Offshore #_DataCard2": 218,
    "Onsite #_DataCard1": 427,
    "Onsite #_DataCard1_1": 542,
    "Onsite #_DataCard2": 213,
    "Onsite/offshore_DataCard1": 89,
    "Onsite/offshore_DataCard2": 43,
    "P&L %_DataCard1": 139,
    "P&L %_DataCard2": 55,
    "P&L_DataCard1": 134,
    "P&L_DataCard2": 54,
    "Project code_DataCard1": 382,
    "Project code_DataCard1_1": 497,
    "Project code_DataCard2": 189,
    "Project Dashboard Screen": 318,
    "Project end date_DataCard1": 412,
    "Project end date_DataCard1_1": 527,
    "Project end date_DataCard2": 198,
    "Project Manager_DataCard1": 392,
    "Project Manager_DataCard1_1": 507,
    "Project Manager_DataCard2": 39,
    "Project Manager_DataCard3": 191,
    "Project Manager_DataCard4": 75,
    "Project Name_DataCard1": 387,
    "Project Name_DataCard1_1": 502,
    "Project Name_DataCard2": 190,
    "Project Start Date_DataCard1": 407,
    "Project Start Date_DataCard1_1": 522,
    "Project Start Date_DataCard2": 194,
    "Project status_DataCard1": 467,
    "Project status_DataCard1_1": 582,
    "Project status_DataCard2": 263,
    "Quarter_DataCard2": 58,
    "Quarter_DataCard3": 253,
    "Quarter_DataCard4": 154,
    "rct_Header": 5,
    "rct_Header_1": 28,
    "rct_Header_2": 11,
    "rct_Login": 356,
    "rct_Login1": 354,
    "record comments_DataCard1": 70,
    "Record comments_DataCard1": 303,
    "Record status_DataCard1": 298,
    "Record status_DataCard3": 174,
    "Rectangle1": 16,
    "Rectangle2": 20,
    "Revenue Year_DataCard1": 159,
    "Revenue Year_DataCard2": 59,
    "Revenue_DataCard1": 124,
    "Revenue_DataCard2": 52,
    "Risk Status (RAG)_DataCard1": 268,
    "Schedule variance (# days)_DataCard1": 288,
    "Separator": 630,
    "Separator_1": 352,
    "StarVisible1": 375,
    "StarVisible1_1": 490,
    "StarVisible10": 421,
    "StarVisible10_1": 536,
    "StarVisible100": 163,
    "StarVisible101": 168,
    "StarVisible102": 173,
    "StarVisible103": 178,
    "StarVisible104": 74,
    "StarVisible105": 183,
    "StarVisible11": 426,
    "StarVisible11_1": 541,
    "StarVisible12": 431,
    "StarVisible12_1": 546,
    "StarVisible13": 436,
    "StarVisible13_1": 551,
    "StarVisible14": 441,
    "StarVisible14_1": 556,
    "StarVisible15": 446,
    "StarVisible15_1": 561,
    "StarVisible16": 451,
    "StarVisible16_1": 566,
    "StarVisible17": 456,
    "StarVisible17_1": 571,
    "StarVisible18": 461,
    "StarVisible18_1": 576,
    "StarVisible2": 381,
    "StarVisible2_1": 496,
    "StarVisible21": 466,
    "StarVisible21_1": 581,
    "StarVisible22": 471,
    "StarVisible22_1": 586,
    "StarVisible25": 476,
    "StarVisible25_1": 591,
    "StarVisible3": 386,
    "StarVisible3_1": 501,
    "StarVisible31": 481,
    "StarVisible31_1": 596,
    "StarVisible4": 391,
    "StarVisible4_1": 506,
    "StarVisible5": 396,
    "StarVisible5_1": 511,
    "StarVisible56": 197,
    "StarVisible57": 202,
    "StarVisible58": 207,
    "StarVisible59": 212,
    "StarVisible6": 401,
    "StarVisible6_1": 516,
    "StarVisible60": 217,
    "StarVisible61": 222,
    "StarVisible62": 227,
    "StarVisible63": 232,
    "StarVisible64": 237,
    "StarVisible65": 242,
    "StarVisible66": 247,
    "StarVisible67": 252,
    "StarVisible68": 257,
    "StarVisible69": 262,
    "StarVisible7": 406,
    "StarVisible7_1": 521,
    "StarVisible70": 267,
    "StarVisible71": 272,
    "StarVisible72": 277,
    "StarVisible73": 282,
    "StarVisible74": 287,
    "StarVisible75": 292,
    "StarVisible76": 297,
    "StarVisible77": 302,
    "StarVisible78": 307,
    "StarVisible79": 312,
    "StarVisible8": 411,
    "StarVisible8_1": 526,
    "StarVisible80": 317,
    "StarVisible82": 69,
    "StarVisible83": 78,
    "StarVisible84": 83,
    "StarVisible85": 88,
    "StarVisible86": 93,
    "StarVisible87": 98,
    "StarVisible88": 103,
    "StarVisible89": 108,
    "StarVisible9": 416,
    "StarVisible9_1": 531,
    "StarVisible90": 113,
    "StarVisible91": 118,
    "StarVisible92": 123,
    "StarVisible93": 128,
    "StarVisible94": 133,
    "StarVisible95": 138,
    "StarVisible96": 143,
    "StarVisible97": 148,
    "StarVisible98": 153,
    "StarVisible99": 158,
    "Tax %_DataCard1": 114,
    "Tax %_DataCard2": 50,
    "Tax Amount in Usd_DataCard1": 119,
    "Tax Amount in Usd_DataCard2": 51,
    "TextInput1": 600,
    "TextInput1_1": 320,
    "TextInput2": 604,
    "TextInput2_1": 323,
    "TextInput3": 606,
    "TextInput3_1": 326,
    "TextInput3_2": 332,
    "Total #_DataCard1": 437,
    "Total #_DataCard1_1": 552,
    "Total #_DataCard2": 223,
    "Total Cost in USD_DataCard1": 422,
    "Total Cost in USD_DataCard1_1": 537,
    "Total Cost in USD_DataCard2": 208,
    "txt_Password": 361,
    "txt_Username": 359,
    "Type of contract_DataCard1": 462,
    "Type of contract_DataCard1_1": 577,
    "Type of contract_DataCard2": 258,
    "Type of Engagement_DataCard1": 417,
    "Type of Engagement_DataCard1_1": 532,
    "Type of Engagement_DataCard2": 203,
    "Type of project_DataCard1": 472,
    "Type of project_DataCard1_1": 587,
    "Type of project_DataCard2": 278,
    "Upload DM approval email _DataCard1": 293,
    "year_DataCard2": 248
  },
  "FunctionParamsInvariantScripts": {},
  "FunctionParamsInvariantScriptsOnInstances": {},
  "HeaderLastSavedDateTimeUTC": "09/25/2023 05:23:44",
  "IsLegacyComponentAllowGlobalScopeCase": false,
  "LocalConnectionIDReferences": {
    "c353e36c-7f67-4df5-8123-1678d478645c": "\"/providers/microsoft.powerapps/apis/shared_sharepointonline/connections/7f17d42ce7404c7391d1fa78edffc41f\""
  },
  "LocalDatabaseReferencesAsEmpty": false,
  "LocalResourceFileNames": {
    "Coforge logo (1)": "0001.png",
    "COFORGE.NS_BIG-6fe17054": "0002.png"
  },
  "LocalResourceRootPaths": {
    "Coforge logo (1)": "https://docserverpwaprodsin.blob.core.windows.net/08f63ea8-f42c-4e9d-874d-c59e97099d81-1/resource/Assets0Images00001.png?sv=2018-03-28&sr=b&sig=%2B1J26AAKIdKXTS7DpjZYn4k7gakq3%2F50RWWpNwg3BsU%3D&spr=https&se=2023-09-26T05%3A07%3A51Z&sp=r",
    "COFORGE.NS_BIG-6fe17054": "https://docserverpwaprodsin.blob.core.windows.net/08f63ea8-f42c-4e9d-874d-c59e97099d81-1/resource/Assets0Images00002.png?sv=2018-03-28&sr=b&sig=O4%2FMCjbYvVgucS%2BajnQZmoRNJ8p7o0i3VKmdK6rXw28%3D&spr=https&se=2023-09-26T05%3A07%3A51Z&sp=r"
  },
  "OrderComponentMetadata": {
    "3117ead71d154f21b8f2684993e2a127": 1,
    "4832bbbf1ea84dd6925ae3108c0252ee": 3,
    "ba4b9730a2a542e9a6d7429ca58b71bc": 2,
    "e20a402af7de411fa32417369e90a871": 0
  },
  "OrderComponentTemplate": {
    "3117ead71d154f21b8f2684993e2a127": 1,
    "4832bbbf1ea84dd6925ae3108c0252ee": 3,
    "ba4b9730a2a542e9a6d7429ca58b71bc": 2,
    "e20a402af7de411fa32417369e90a871": 0
  },
  "OrderDataSource": {
    "Account list- AMS": 0,
    "AMS-Roles": 1,
    "CustomGallerySample": 2,
    "DropDownSample": 3,
    "Project list_AMS": 4
  },
  "OrderGroupControls": {
    "Group": {
      "img_CompanyLogo": 1,
      "lbl_ClaimsLoginHeader": 2,
      "rct_Header_2": 0
    },
    "grp_header": {
      "Image1": 1,
      "Label1": 2,
      "Rectangle1": 0
    },
    "grp_logout": {
      "Button1": 3,
      "Icon1": 0,
      "Icon2": 2,
      "Icon3": 4,
      "Label2": 5,
      "Rectangle2": 1
    }
  },
  "OrderPcfTemplate": {},
  "OrderTemplate": {},
  "OrderXMLTemplate": {
    "attachments": 5,
    "button": 6,
    "datepicker": 4,
    "dropdown": 1,
    "form": 0,
    "gallery": 10,
    "icon": 9,
    "image": 8,
    "label": 3,
    "rectangle": 7,
    "text": 2
  },
  "OverridablePropertiesEntry": {
    "# projects_DataCard1": {},
    "# projects_DataCard2": {},
    "Account Cost in USD_DataCard1": {},
    "Account Cost in USD_DataCard2": {},
    "Account Dashboard Screen": {},
    "Account End date_DataCard1": {},
    "Account End date_DataCard2": {},
    "Account Name_DataCard1": {},
    "Account Name_DataCard1_1": {},
    "Account Name_DataCard2": {},
    "Account Name_DataCard3": {},
    "Account Name_DataCard4": {},
    "Account Start date_DataCard1": {},
    "Account Start date_DataCard2": {},
    "Account Status_DataCard1": {},
    "Account Status_DataCard2": {},
    "Add a new account": {},
    "App": {},
    "Approval for Project": {},
    "Attachments_DataCard2": {},
    "Attachments_DataCard3": {},
    "Blended rate in USD_DataCard1": {},
    "Blended rate in USD_DataCard1_1": {},
    "Blended rate in USD_DataCard2": {},
    "Blended rate offshore (Per Month in USD)_DataCard1": {},
    "Blended rate offshore (Per Month in USD)_DataCard1_1": {},
    "Blended rate offshore (Per Month in USD)_DataCard2": {},
    "Blended rate onsite (Per Month in USD)_DataCard1": {},
    "Blended rate onsite (Per Month in USD)_DataCard1_1": {},
    "Blended rate onsite (Per Month in USD)_DataCard2": {},
    "btn_Notification": {},
    "btn_Signin": {},
    "Button1": {},
    "Button2": {},
    "Button2_1": {},
    "Button3": {},
    "Button3_1": {},
    "Button4": {},
    "Button4_1": {},
    "Button5": {},
    "Button5_1": {},
    "Button6": {},
    "Button6_1": {},
    "cmt_Header": {},
    "cmt_Header_1": {},
    "cmt_Header_2": {},
    "cmt_InsuranceHeader": {},
    "cmt_loginHeader": {},
    "cmt_loginHeader_1": {},
    "Comments_DataCard1": {},
    "Comments_DataCard1_1": {},
    "Comments_DataCard2": {},
    "Component1_1": {},
    "Cost_DataCard1": {},
    "Cost_DataCard2": {},
    "Currency_DataCard1": {},
    "Currency_DataCard2": {},
    "DataCardKey1": {},
    "DataCardKey1_1": {},
    "DataCardKey10": {},
    "DataCardKey10_1": {},
    "DataCardKey100": {},
    "DataCardKey101": {},
    "DataCardKey102": {},
    "DataCardKey103": {},
    "DataCardKey104": {},
    "DataCardKey105": {},
    "DataCardKey11": {},
    "DataCardKey11_1": {},
    "DataCardKey12": {},
    "DataCardKey12_1": {},
    "DataCardKey13": {},
    "DataCardKey13_1": {},
    "DataCardKey14": {},
    "DataCardKey14_1": {},
    "DataCardKey15": {},
    "DataCardKey15_1": {},
    "DataCardKey16": {},
    "DataCardKey16_1": {},
    "DataCardKey17": {},
    "DataCardKey17_1": {},
    "DataCardKey18": {},
    "DataCardKey18_1": {},
    "DataCardKey2": {},
    "DataCardKey2_1": {},
    "DataCardKey21": {},
    "DataCardKey21_1": {},
    "DataCardKey22": {},
    "DataCardKey22_1": {},
    "DataCardKey25": {},
    "DataCardKey25_1": {},
    "DataCardKey3": {},
    "DataCardKey3_1": {},
    "DataCardKey31": {},
    "DataCardKey31_1": {},
    "DataCardKey4": {},
    "DataCardKey4_1": {},
    "DataCardKey5": {},
    "DataCardKey5_1": {},
    "DataCardKey56": {},
    "DataCardKey57": {},
    "DataCardKey58": {},
    "DataCardKey59": {},
    "DataCardKey6": {},
    "DataCardKey6_1": {},
    "DataCardKey60": {},
    "DataCardKey61": {},
    "DataCardKey62": {},
    "DataCardKey63": {},
    "DataCardKey64": {},
    "DataCardKey65": {},
    "DataCardKey66": {},
    "DataCardKey67": {},
    "DataCardKey68": {},
    "DataCardKey69": {},
    "DataCardKey7": {},
    "DataCardKey7_1": {},
    "DataCardKey70": {},
    "DataCardKey71": {},
    "DataCardKey72": {},
    "DataCardKey73": {},
    "DataCardKey74": {},
    "DataCardKey75": {},
    "DataCardKey76": {},
    "DataCardKey77": {},
    "DataCardKey78": {},
    "DataCardKey79": {},
    "DataCardKey8": {},
    "DataCardKey8_1": {},
    "DataCardKey80": {},
    "DataCardKey82": {},
    "DataCardKey83": {},
    "DataCardKey84": {},
    "DataCardKey85": {},
    "DataCardKey86": {},
    "DataCardKey87": {},
    "DataCardKey88": {},
    "DataCardKey89": {},
    "DataCardKey9": {},
    "DataCardKey9_1": {},
    "DataCardKey90": {},
    "DataCardKey91": {},
    "DataCardKey92": {},
    "DataCardKey93": {},
    "DataCardKey94": {},
    "DataCardKey95": {},
    "DataCardKey96": {},
    "DataCardKey97": {},
    "DataCardKey98": {},
    "DataCardKey99": {},
    "DataCardValue11": {},
    "DataCardValue11_1": {},
    "DataCardValue12": {},
    "DataCardValue12_1": {},
    "DataCardValue13": {},
    "DataCardValue13_1": {},
    "DataCardValue14": {},
    "DataCardValue14_1": {},
    "DataCardValue15": {},
    "DataCardValue15_1": {},
    "DataCardValue16": {},
    "DataCardValue16_1": {},
    "DataCardValue17": {},
    "DataCardValue17_1": {},
    "DataCardValue18": {},
    "DataCardValue18_1": {},
    "DataCardValue20": {},
    "DataCardValue21": {},
    "DataCardValue22": {},
    "DataCardValue25": {},
    "DataCardValue3": {},
    "DataCardValue3_1": {},
    "DataCardValue31": {},
    "DataCardValue31_1": {},
    "DataCardValue4": {},
    "DataCardValue4_1": {},
    "DataCardValue5": {},
    "DataCardValue5_1": {},
    "DataCardValue51": {},
    "DataCardValue53": {},
    "DataCardValue54": {},
    "DataCardValue55": {},
    "DataCardValue56": {},
    "DataCardValue57": {},
    "DataCardValue58": {},
    "DataCardValue59": {},
    "DataCardValue6": {},
    "DataCardValue6_1": {},
    "DataCardValue60": {},
    "DataCardValue61": {},
    "DataCardValue62": {},
    "DataCardValue63": {},
    "DataCardValue64": {},
    "DataCardValue65": {},
    "DataCardValue66": {},
    "DataCardValue67": {},
    "DataCardValue68": {},
    "DataCardValue69": {},
    "DataCardValue7": {},
    "DataCardValue7_1": {},
    "DataCardValue70": {},
    "DataCardValue71": {},
    "DataCardValue72": {},
    "DataCardValue73": {},
    "DataCardValue74": {},
    "DataCardValue75": {},
    "DataCardValue76": {},
    "DataCardValue77": {},
    "DataCardValue78": {},
    "DataCardValue79": {},
    "DataCardValue8": {},
    "DataCardValue8_1": {},
    "DataCardValue80": {},
    "DataCardValue81": {},
    "DataCardValue82": {},
    "DataCardValue83": {},
    "DataCardValue84": {},
    "DataCardValue85": {},
    "DataCardValue86": {},
    "DataCardValue87": {},
    "DataCardValue88": {},
    "DataCardValue89": {},
    "DataCardValue9": {},
    "DataCardValue9_1": {},
    "DataCardValue90": {},
    "DataCardValue91": {},
    "DataCardValue92": {},
    "DataCardValue93": {},
    "DataCardValue94": {},
    "DataCardValue95": {},
    "DataCardValue96": {},
    "DataCardValue97": {},
    "DataCardValue98": {},
    "Deepdiving Each Account Record": {},
    "Deepdiving Each Project Record": {},
    "Delivery Head_DataCard1": {},
    "Delivery Head_DataCard1_1": {},
    "Delivery Head_DataCard2": {},
    "Delivery Head_DataCard3": {},
    "Delivery Head_DataCard4": {},
    "Delivery Manager_DataCard1": {},
    "Delivery Manager_DataCard1_1": {},
    "Delivery Manager_DataCard2": {},
    "Delivery Manager_DataCard3": {},
    "Delivery Manager_DataCard4": {},
    "Dropdown1": {},
    "Dropdown1_1": {},
    "Dropdown2": {},
    "Dropdown2_1": {},
    "Dropdown3": {},
    "Dropdown3_1": {},
    "Dropdown4": {},
    "Dropdown5": {},
    "Dropdown5_1": {},
    "Dropdown6": {},
    "Dropdown6_1": {},
    "Dropdown7": {},
    "Dropdown7_1": {},
    "Duration in yr_DataCard1": {},
    "Duration in yr_DataCard2": {},
    "Effort Slippage (in days)_DataCard1": {},
    "ErrorMessage1": {},
    "ErrorMessage1_1": {},
    "ErrorMessage10": {},
    "ErrorMessage10_1": {},
    "ErrorMessage100": {},
    "ErrorMessage101": {},
    "ErrorMessage102": {},
    "ErrorMessage103": {},
    "ErrorMessage104": {},
    "ErrorMessage105": {},
    "ErrorMessage11": {},
    "ErrorMessage11_1": {},
    "ErrorMessage12": {},
    "ErrorMessage12_1": {},
    "ErrorMessage13": {},
    "ErrorMessage13_1": {},
    "ErrorMessage14": {},
    "ErrorMessage14_1": {},
    "ErrorMessage15": {},
    "ErrorMessage15_1": {},
    "ErrorMessage16": {},
    "ErrorMessage16_1": {},
    "ErrorMessage17": {},
    "ErrorMessage17_1": {},
    "ErrorMessage18": {},
    "ErrorMessage18_1": {},
    "ErrorMessage2": {},
    "ErrorMessage2_1": {},
    "ErrorMessage21": {},
    "ErrorMessage21_1": {},
    "ErrorMessage22": {},
    "ErrorMessage22_1": {},
    "ErrorMessage25": {},
    "ErrorMessage25_1": {},
    "ErrorMessage3": {},
    "ErrorMessage3_1": {},
    "ErrorMessage31": {},
    "ErrorMessage31_1": {},
    "ErrorMessage4": {},
    "ErrorMessage4_1": {},
    "ErrorMessage5": {},
    "ErrorMessage5_1": {},
    "ErrorMessage56": {},
    "ErrorMessage57": {},
    "ErrorMessage58": {},
    "ErrorMessage59": {},
    "ErrorMessage6": {},
    "ErrorMessage6_1": {},
    "ErrorMessage60": {},
    "ErrorMessage61": {},
    "ErrorMessage62": {},
    "ErrorMessage63": {},
    "ErrorMessage64": {},
    "ErrorMessage65": {},
    "ErrorMessage66": {},
    "ErrorMessage67": {},
    "ErrorMessage68": {},
    "ErrorMessage69": {},
    "ErrorMessage7": {},
    "ErrorMessage7_1": {},
    "ErrorMessage70": {},
    "ErrorMessage71": {},
    "ErrorMessage72": {},
    "ErrorMessage73": {},
    "ErrorMessage74": {},
    "ErrorMessage75": {},
    "ErrorMessage76": {},
    "ErrorMessage77": {},
    "ErrorMessage78": {},
    "ErrorMessage79": {},
    "ErrorMessage8": {},
    "ErrorMessage8_1": {},
    "ErrorMessage80": {},
    "ErrorMessage82": {},
    "ErrorMessage83": {},
    "ErrorMessage84": {},
    "ErrorMessage85": {},
    "ErrorMessage86": {},
    "ErrorMessage87": {},
    "ErrorMessage88": {},
    "ErrorMessage89": {},
    "ErrorMessage9": {},
    "ErrorMessage9_1": {},
    "ErrorMessage90": {},
    "ErrorMessage91": {},
    "ErrorMessage92": {},
    "ErrorMessage93": {},
    "ErrorMessage94": {},
    "ErrorMessage95": {},
    "ErrorMessage96": {},
    "ErrorMessage97": {},
    "ErrorMessage98": {},
    "ErrorMessage99": {},
    "Execution Status_DataCard1": {},
    "Form1": {},
    "Form1_1": {},
    "Form2": {},
    "Form3": {},
    "Form4": {},
    "gal_AccountList": {},
    "gal_AccountList_1": {},
    "galleryTemplate3_1": {},
    "galleryTemplate3_2": {},
    "Geo_DataCard1": {},
    "Geo_DataCard1_1": {},
    "Geo_DataCard2": {},
    "GM %_DataCard1": {},
    "GM %_DataCard1_1": {},
    "GM %_DataCard2": {},
    "Gross Margin %_DataCard1": {},
    "Gross Margin %_DataCard2": {},
    "Group": {},
    "grp_header": {},
    "grp_logout": {},
    "Host": {},
    "ico_EyeIcon": {},
    "ico_Notification": {},
    "ico_Userdetailsdownarrow": {},
    "Icon1": {},
    "Icon2": {},
    "Icon3": {},
    "Image1": {},
    "Img_CompantLogo": {},
    "Img_CompantLogo_1": {},
    "img_CompanyLogo": {},
    "Img_User": {},
    "Img_User_1": {},
    "Label1": {},
    "Label2": {},
    "Label3": {},
    "Label3_1": {},
    "Label4": {},
    "Label4_1": {},
    "Label5": {},
    "Label5_1": {},
    "Label5_2": {},
    "Label6": {},
    "Label6_1": {},
    "lbl_#Projects": {},
    "lbl_#projects_1": {},
    "lbl_#Projects_1": {},
    "lbl_#projects_2": {},
    "lbl_AccountcostinUSD": {},
    "lbl_AccountcostinUSD_1": {},
    "lbl_AccountcostinUSD_2": {},
    "lbl_AccountcostinUSD_3": {},
    "lbl_Accountname": {},
    "lbl_Accountname_1": {},
    "lbl_Accountname_2": {},
    "lbl_Accountname_3": {},
    "lbl_Blank": {},
    "lbl_Blank_1": {},
    "lbl_ClaimsLoginHeader": {},
    "lbl_Cost": {},
    "lbl_Cost_1": {},
    "lbl_Cost_2": {},
    "lbl_Cost_3": {},
    "lbl_Country": {},
    "lbl_Country_1": {},
    "lbl_Country_2": {},
    "lbl_Country_3": {},
    "lbl_Don't have an account?": {},
    "lbl_errormessage for username and password": {},
    "lbl_Forgotpassword": {},
    "lbl_Geo": {},
    "lbl_Geo_1": {},
    "lbl_Geo_2": {},
    "lbl_Geo_3": {},
    "lbl_Grossmargin%": {},
    "lbl_Grossmargin%_1": {},
    "lbl_Grossmargin%_2": {},
    "lbl_Grossmargin%_3": {},
    "lbl_Insurance": {},
    "lbl_Login": {},
    "lbl_P&L": {},
    "lbl_P&L_1": {},
    "lbl_P&L_2": {},
    "lbl_P&L_3": {},
    "lbl_Password": {},
    "lbl_Revenue": {},
    "lbl_Revenue_1": {},
    "lbl_Revenue_2": {},
    "lbl_Revenue_3": {},
    "lbl_UserName": {},
    "lbl_UserName_1": {},
    "lbl-Username": {},
    "Login": {},
    "New Project": {},
    "New Project_1": {},
    "NextArrow": {},
    "Offshore #_DataCard1": {},
    "Offshore #_DataCard1_1": {},
    "Offshore #_DataCard2": {},
    "Onsite #_DataCard1": {},
    "Onsite #_DataCard1_1": {},
    "Onsite #_DataCard2": {},
    "Onsite/offshore_DataCard1": {},
    "Onsite/offshore_DataCard2": {},
    "P&L %_DataCard1": {},
    "P&L %_DataCard2": {},
    "P&L_DataCard1": {},
    "P&L_DataCard2": {},
    "Project code_DataCard1": {},
    "Project code_DataCard1_1": {},
    "Project code_DataCard2": {},
    "Project Dashboard Screen": {},
    "Project end date_DataCard1": {},
    "Project end date_DataCard1_1": {},
    "Project end date_DataCard2": {},
    "Project Manager_DataCard1": {},
    "Project Manager_DataCard1_1": {},
    "Project Manager_DataCard2": {},
    "Project Manager_DataCard3": {},
    "Project Manager_DataCard4": {},
    "Project Name_DataCard1": {},
    "Project Name_DataCard1_1": {},
    "Project Name_DataCard2": {},
    "Project Start Date_DataCard1": {},
    "Project Start Date_DataCard1_1": {},
    "Project Start Date_DataCard2": {},
    "Project status_DataCard1": {},
    "Project status_DataCard1_1": {},
    "Project status_DataCard2": {},
    "Quarter_DataCard2": {},
    "Quarter_DataCard3": {},
    "Quarter_DataCard4": {},
    "rct_Header": {},
    "rct_Header_1": {},
    "rct_Header_2": {},
    "rct_Login": {},
    "rct_Login1": {},
    "record comments_DataCard1": {},
    "Record comments_DataCard1": {},
    "Record status_DataCard1": {},
    "Record status_DataCard3": {},
    "Rectangle1": {},
    "Rectangle2": {},
    "Revenue Year_DataCard1": {},
    "Revenue Year_DataCard2": {},
    "Revenue_DataCard1": {},
    "Revenue_DataCard2": {},
    "Risk Status (RAG)_DataCard1": {},
    "Schedule variance (# days)_DataCard1": {},
    "Separator": {},
    "Separator_1": {},
    "StarVisible1": {},
    "StarVisible1_1": {},
    "StarVisible10": {},
    "StarVisible10_1": {},
    "StarVisible100": {},
    "StarVisible101": {},
    "StarVisible102": {},
    "StarVisible103": {},
    "StarVisible104": {},
    "StarVisible105": {},
    "StarVisible11": {},
    "StarVisible11_1": {},
    "StarVisible12": {},
    "StarVisible12_1": {},
    "StarVisible13": {},
    "StarVisible13_1": {},
    "StarVisible14": {},
    "StarVisible14_1": {},
    "StarVisible15": {},
    "StarVisible15_1": {},
    "StarVisible16": {},
    "StarVisible16_1": {},
    "StarVisible17": {},
    "StarVisible17_1": {},
    "StarVisible18": {},
    "StarVisible18_1": {},
    "StarVisible2": {},
    "StarVisible2_1": {},
    "StarVisible21": {},
    "StarVisible21_1": {},
    "StarVisible22": {},
    "StarVisible22_1": {},
    "StarVisible25": {},
    "StarVisible25_1": {},
    "StarVisible3": {},
    "StarVisible3_1": {},
    "StarVisible31": {},
    "StarVisible31_1": {},
    "StarVisible4": {},
    "StarVisible4_1": {},
    "StarVisible5": {},
    "StarVisible5_1": {},
    "StarVisible56": {},
    "StarVisible57": {},
    "StarVisible58": {},
    "StarVisible59": {},
    "StarVisible6": {},
    "StarVisible6_1": {},
    "StarVisible60": {},
    "StarVisible61": {},
    "StarVisible62": {},
    "StarVisible63": {},
    "StarVisible64": {},
    "StarVisible65": {},
    "StarVisible66": {},
    "StarVisible67": {},
    "StarVisible68": {},
    "StarVisible69": {},
    "StarVisible7": {},
    "StarVisible7_1": {},
    "StarVisible70": {},
    "StarVisible71": {},
    "StarVisible72": {},
    "StarVisible73": {},
    "StarVisible74": {},
    "StarVisible75": {},
    "StarVisible76": {},
    "StarVisible77": {},
    "StarVisible78": {},
    "StarVisible79": {},
    "StarVisible8": {},
    "StarVisible8_1": {},
    "StarVisible80": {},
    "StarVisible82": {},
    "StarVisible83": {},
    "StarVisible84": {},
    "StarVisible85": {},
    "StarVisible86": {},
    "StarVisible87": {},
    "StarVisible88": {},
    "StarVisible89": {},
    "StarVisible9": {},
    "StarVisible9_1": {},
    "StarVisible90": {},
    "StarVisible91": {},
    "StarVisible92": {},
    "StarVisible93": {},
    "StarVisible94": {},
    "StarVisible95": {},
    "StarVisible96": {},
    "StarVisible97": {},
    "StarVisible98": {},
    "StarVisible99": {},
    "Tax %_DataCard1": {},
    "Tax %_DataCard2": {},
    "Tax Amount in Usd_DataCard1": {},
    "Tax Amount in Usd_DataCard2": {},
    "TextInput1": {},
    "TextInput1_1": {},
    "TextInput2": {},
    "TextInput2_1": {},
    "TextInput3": {},
    "TextInput3_1": {},
    "TextInput3_2": {},
    "Total #_DataCard1": {},
    "Total #_DataCard1_1": {},
    "Total #_DataCard2": {},
    "Total Cost in USD_DataCard1": {},
    "Total Cost in USD_DataCard1_1": {},
    "Total Cost in USD_DataCard2": {},
    "txt_Password": {},
    "txt_Username": {},
    "Type of contract_DataCard1": {},
    "Type of contract_DataCard1_1": {},
    "Type of contract_DataCard2": {},
    "Type of Engagement_DataCard1": {},
    "Type of Engagement_DataCard1_1": {},
    "Type of Engagement_DataCard2": {},
    "Type of project_DataCard1": {},
    "Type of project_DataCard1_1": {},
    "Type of project_DataCard2": {},
    "Upload DM approval email _DataCard1": {},
    "year_DataCard2": {}
  },
  "PCFDynamicSchemaForIRRetrievalEntry": {},
  "PCFTemplateEntry": {},
  "PublishOrderIndices": {
    "# projects_DataCard1": 104,
    "# projects_DataCard2": 73,
    "Account Cost in USD_DataCard1": 106,
    "Account Cost in USD_DataCard2": 75,
    "Account Dashboard Screen": 32,
    "Account End date_DataCard1": 115,
    "Account End date_DataCard2": 84,
    "Account Name_DataCard1": 370,
    "Account Name_DataCard1_1": 370,
    "Account Name_DataCard2": 68,
    "Account Name_DataCard3": 219,
    "Account Name_DataCard4": 98,
    "Account Start date_DataCard1": 114,
    "Account Start date_DataCard2": 83,
    "Account Status_DataCard1": 119,
    "Account Status_DataCard2": 88,
    "Add a new account": 66,
    "App": 0,
    "Approval for Project": 95,
    "Attachments_DataCard2": 250,
    "Attachments_DataCard3": 121,
    "Blended rate in USD_DataCard1": 387,
    "Blended rate in USD_DataCard1_1": 387,
    "Blended rate in USD_DataCard2": 236,
    "Blended rate offshore (Per Month in USD)_DataCard1": 385,
    "Blended rate offshore (Per Month in USD)_DataCard1_1": 385,
    "Blended rate offshore (Per Month in USD)_DataCard2": 234,
    "Blended rate onsite (Per Month in USD)_DataCard1": 386,
    "Blended rate onsite (Per Month in USD)_DataCard1_1": 386,
    "Blended rate onsite (Per Month in USD)_DataCard2": 235,
    "btn_Notification": 6,
    "btn_Signin": 363,
    "Button1": 28,
    "Button2": 34,
    "Button2_1": 483,
    "Button3": 36,
    "Button3_1": 486,
    "Button4": 366,
    "Button4_1": 366,
    "Button5": 367,
    "Button5_1": 367,
    "Button6": 368,
    "Button6_1": 368,
    "cmt_Header": 1,
    "cmt_Header_1": 42,
    "cmt_Header_2": 491,
    "cmt_InsuranceHeader": 9,
    "cmt_loginHeader": 15,
    "cmt_loginHeader_1": 353,
    "Comments_DataCard1": 391,
    "Comments_DataCard1_1": 391,
    "Comments_DataCard2": 249,
    "Component1_1": 20,
    "Cost_DataCard1": 111,
    "Cost_DataCard2": 80,
    "Currency_DataCard1": 105,
    "Currency_DataCard2": 74,
    "DataCardKey1": 392,
    "DataCardKey1_1": 392,
    "DataCardKey10": 429,
    "DataCardKey10_1": 429,
    "DataCardKey100": 197,
    "DataCardKey101": 201,
    "DataCardKey102": 205,
    "DataCardKey103": 209,
    "DataCardKey104": 126,
    "DataCardKey105": 213,
    "DataCardKey11": 432,
    "DataCardKey11_1": 432,
    "DataCardKey12": 436,
    "DataCardKey12_1": 436,
    "DataCardKey13": 440,
    "DataCardKey13_1": 440,
    "DataCardKey14": 444,
    "DataCardKey14_1": 444,
    "DataCardKey15": 448,
    "DataCardKey15_1": 448,
    "DataCardKey16": 452,
    "DataCardKey16_1": 452,
    "DataCardKey17": 456,
    "DataCardKey17_1": 456,
    "DataCardKey18": 460,
    "DataCardKey18_1": 460,
    "DataCardKey2": 397,
    "DataCardKey2_1": 397,
    "DataCardKey21": 464,
    "DataCardKey21_1": 464,
    "DataCardKey22": 468,
    "DataCardKey22_1": 468,
    "DataCardKey25": 472,
    "DataCardKey25_1": 472,
    "DataCardKey3": 400,
    "DataCardKey3_1": 400,
    "DataCardKey31": 476,
    "DataCardKey31_1": 476,
    "DataCardKey4": 404,
    "DataCardKey4_1": 404,
    "DataCardKey5": 408,
    "DataCardKey5_1": 408,
    "DataCardKey56": 252,
    "DataCardKey57": 255,
    "DataCardKey58": 259,
    "DataCardKey59": 263,
    "DataCardKey6": 412,
    "DataCardKey6_1": 412,
    "DataCardKey60": 267,
    "DataCardKey61": 271,
    "DataCardKey62": 275,
    "DataCardKey63": 279,
    "DataCardKey64": 283,
    "DataCardKey65": 287,
    "DataCardKey66": 291,
    "DataCardKey67": 295,
    "DataCardKey68": 299,
    "DataCardKey69": 303,
    "DataCardKey7": 416,
    "DataCardKey7_1": 416,
    "DataCardKey70": 307,
    "DataCardKey71": 311,
    "DataCardKey72": 315,
    "DataCardKey73": 319,
    "DataCardKey74": 323,
    "DataCardKey75": 327,
    "DataCardKey76": 331,
    "DataCardKey77": 335,
    "DataCardKey78": 339,
    "DataCardKey79": 343,
    "DataCardKey8": 420,
    "DataCardKey8_1": 420,
    "DataCardKey80": 347,
    "DataCardKey82": 122,
    "DataCardKey83": 130,
    "DataCardKey84": 133,
    "DataCardKey85": 137,
    "DataCardKey86": 141,
    "DataCardKey87": 145,
    "DataCardKey88": 149,
    "DataCardKey89": 153,
    "DataCardKey9": 424,
    "DataCardKey9_1": 424,
    "DataCardKey90": 157,
    "DataCardKey91": 161,
    "DataCardKey92": 165,
    "DataCardKey93": 169,
    "DataCardKey94": 173,
    "DataCardKey95": 177,
    "DataCardKey96": 181,
    "DataCardKey97": 185,
    "DataCardKey98": 189,
    "DataCardKey99": 193,
    "DataCardValue11": 433,
    "DataCardValue11_1": 433,
    "DataCardValue12": 437,
    "DataCardValue12_1": 437,
    "DataCardValue13": 441,
    "DataCardValue13_1": 441,
    "DataCardValue14": 445,
    "DataCardValue14_1": 445,
    "DataCardValue15": 449,
    "DataCardValue15_1": 449,
    "DataCardValue16": 453,
    "DataCardValue16_1": 453,
    "DataCardValue17": 457,
    "DataCardValue17_1": 457,
    "DataCardValue18": 461,
    "DataCardValue18_1": 461,
    "DataCardValue20": 251,
    "DataCardValue21": 90,
    "DataCardValue22": 91,
    "DataCardValue25": 92,
    "DataCardValue3": 401,
    "DataCardValue3_1": 401,
    "DataCardValue31": 477,
    "DataCardValue31_1": 477,
    "DataCardValue4": 405,
    "DataCardValue4_1": 405,
    "DataCardValue5": 409,
    "DataCardValue5_1": 409,
    "DataCardValue51": 123,
    "DataCardValue53": 256,
    "DataCardValue54": 260,
    "DataCardValue55": 264,
    "DataCardValue56": 268,
    "DataCardValue57": 272,
    "DataCardValue58": 276,
    "DataCardValue59": 280,
    "DataCardValue6": 413,
    "DataCardValue6_1": 413,
    "DataCardValue60": 284,
    "DataCardValue61": 288,
    "DataCardValue62": 292,
    "DataCardValue63": 296,
    "DataCardValue64": 300,
    "DataCardValue65": 304,
    "DataCardValue66": 308,
    "DataCardValue67": 312,
    "DataCardValue68": 316,
    "DataCardValue69": 320,
    "DataCardValue7": 417,
    "DataCardValue7_1": 417,
    "DataCardValue70": 324,
    "DataCardValue71": 328,
    "DataCardValue72": 332,
    "DataCardValue73": 336,
    "DataCardValue74": 340,
    "DataCardValue75": 344,
    "DataCardValue76": 348,
    "DataCardValue77": 134,
    "DataCardValue78": 138,
    "DataCardValue79": 142,
    "DataCardValue8": 421,
    "DataCardValue8_1": 421,
    "DataCardValue80": 146,
    "DataCardValue81": 150,
    "DataCardValue82": 154,
    "DataCardValue83": 158,
    "DataCardValue84": 162,
    "DataCardValue85": 166,
    "DataCardValue86": 170,
    "DataCardValue87": 174,
    "DataCardValue88": 178,
    "DataCardValue89": 182,
    "DataCardValue9": 425,
    "DataCardValue9_1": 425,
    "DataCardValue90": 186,
    "DataCardValue91": 190,
    "DataCardValue92": 194,
    "DataCardValue93": 198,
    "DataCardValue94": 202,
    "DataCardValue95": 206,
    "DataCardValue96": 210,
    "DataCardValue97": 127,
    "DataCardValue98": 214,
    "Deepdiving Each Account Record": 96,
    "Deepdiving Each Project Record": 217,
    "Delivery Head_DataCard1": 376,
    "Delivery Head_DataCard1_1": 376,
    "Delivery Head_DataCard2": 71,
    "Delivery Head_DataCard3": 225,
    "Delivery Head_DataCard4": 102,
    "Delivery Manager_DataCard1": 375,
    "Delivery Manager_DataCard1_1": 375,
    "Delivery Manager_DataCard2": 70,
    "Delivery Manager_DataCard3": 224,
    "Delivery Manager_DataCard4": 101,
    "Dropdown1": 395,
    "Dropdown1_1": 395,
    "Dropdown2": 396,
    "Dropdown2_1": 396,
    "Dropdown3": 428,
    "Dropdown3_1": 428,
    "Dropdown4": 89,
    "Dropdown5": 465,
    "Dropdown5_1": 465,
    "Dropdown6": 469,
    "Dropdown6_1": 469,
    "Dropdown7": 473,
    "Dropdown7_1": 473,
    "Duration in yr_DataCard1": 118,
    "Duration in yr_DataCard2": 87,
    "Effort Slippage (in days)_DataCard1": 244,
    "ErrorMessage1": 393,
    "ErrorMessage1_1": 393,
    "ErrorMessage10": 430,
    "ErrorMessage10_1": 430,
    "ErrorMessage100": 199,
    "ErrorMessage101": 203,
    "ErrorMessage102": 207,
    "ErrorMessage103": 211,
    "ErrorMessage104": 128,
    "ErrorMessage105": 215,
    "ErrorMessage11": 434,
    "ErrorMessage11_1": 434,
    "ErrorMessage12": 438,
    "ErrorMessage12_1": 438,
    "ErrorMessage13": 442,
    "ErrorMessage13_1": 442,
    "ErrorMessage14": 446,
    "ErrorMessage14_1": 446,
    "ErrorMessage15": 450,
    "ErrorMessage15_1": 450,
    "ErrorMessage16": 454,
    "ErrorMessage16_1": 454,
    "ErrorMessage17": 458,
    "ErrorMessage17_1": 458,
    "ErrorMessage18": 462,
    "ErrorMessage18_1": 462,
    "ErrorMessage2": 398,
    "ErrorMessage2_1": 398,
    "ErrorMessage21": 466,
    "ErrorMessage21_1": 466,
    "ErrorMessage22": 470,
    "ErrorMessage22_1": 470,
    "ErrorMessage25": 474,
    "ErrorMessage25_1": 474,
    "ErrorMessage3": 402,
    "ErrorMessage3_1": 402,
    "ErrorMessage31": 478,
    "ErrorMessage31_1": 478,
    "ErrorMessage4": 406,
    "ErrorMessage4_1": 406,
    "ErrorMessage5": 410,
    "ErrorMessage5_1": 410,
    "ErrorMessage56": 253,
    "ErrorMessage57": 257,
    "ErrorMessage58": 261,
    "ErrorMessage59": 265,
    "ErrorMessage6": 414,
    "ErrorMessage6_1": 414,
    "ErrorMessage60": 269,
    "ErrorMessage61": 273,
    "ErrorMessage62": 277,
    "ErrorMessage63": 281,
    "ErrorMessage64": 285,
    "ErrorMessage65": 289,
    "ErrorMessage66": 293,
    "ErrorMessage67": 297,
    "ErrorMessage68": 301,
    "ErrorMessage69": 305,
    "ErrorMessage7": 418,
    "ErrorMessage7_1": 418,
    "ErrorMessage70": 309,
    "ErrorMessage71": 313,
    "ErrorMessage72": 317,
    "ErrorMessage73": 321,
    "ErrorMessage74": 325,
    "ErrorMessage75": 329,
    "ErrorMessage76": 333,
    "ErrorMessage77": 337,
    "ErrorMessage78": 341,
    "ErrorMessage79": 345,
    "ErrorMessage8": 422,
    "ErrorMessage8_1": 422,
    "ErrorMessage80": 349,
    "ErrorMessage82": 124,
    "ErrorMessage83": 131,
    "ErrorMessage84": 135,
    "ErrorMessage85": 139,
    "ErrorMessage86": 143,
    "ErrorMessage87": 147,
    "ErrorMessage88": 151,
    "ErrorMessage89": 155,
    "ErrorMessage9": 426,
    "ErrorMessage9_1": 426,
    "ErrorMessage90": 159,
    "ErrorMessage91": 163,
    "ErrorMessage92": 167,
    "ErrorMessage93": 171,
    "ErrorMessage94": 175,
    "ErrorMessage95": 179,
    "ErrorMessage96": 183,
    "ErrorMessage97": 187,
    "ErrorMessage98": 191,
    "ErrorMessage99": 195,
    "Execution Status_DataCard1": 242,
    "Form1": 369,
    "Form1_1": 369,
    "Form2": 218,
    "Form3": 97,
    "Form4": 67,
    "gal_AccountList": 53,
    "gal_AccountList_1": 503,
    "galleryTemplate3_1": 54,
    "galleryTemplate3_2": 504,
    "Geo_DataCard1": 371,
    "Geo_DataCard1_1": 371,
    "Geo_DataCard2": 220,
    "GM %_DataCard1": 384,
    "GM %_DataCard1_1": 384,
    "GM %_DataCard2": 233,
    "Gross Margin %_DataCard1": 107,
    "Gross Margin %_DataCard2": 76,
    "Group": 19,
    "grp_header": 30,
    "grp_logout": 31,
    "Host": 0,
    "ico_EyeIcon": 360,
    "ico_Notification": 7,
    "ico_Userdetailsdownarrow": 8,
    "Icon1": 24,
    "Icon2": 26,
    "Icon3": 29,
    "Image1": 23,
    "Img_CompantLogo": 11,
    "Img_CompantLogo_1": 3,
    "img_CompanyLogo": 17,
    "Img_User": 13,
    "Img_User_1": 4,
    "Label1": 22,
    "Label2": 27,
    "Label3": 33,
    "Label3_1": 481,
    "Label4": 37,
    "Label4_1": 484,
    "Label5": 40,
    "Label5_1": 487,
    "Label5_2": 490,
    "Label6": 38,
    "Label6_1": 489,
    "lbl_#Projects": 46,
    "lbl_#projects_1": 58,
    "lbl_#Projects_1": 496,
    "lbl_#projects_2": 507,
    "lbl_AccountcostinUSD": 47,
    "lbl_AccountcostinUSD_1": 60,
    "lbl_AccountcostinUSD_2": 509,
    "lbl_AccountcostinUSD_3": 497,
    "lbl_Accountname": 43,
    "lbl_Accountname_1": 59,
    "lbl_Accountname_2": 508,
    "lbl_Accountname_3": 492,
    "lbl_Blank": 52,
    "lbl_Blank_1": 502,
    "lbl_ClaimsLoginHeader": 18,
    "lbl_Cost": 50,
    "lbl_Cost_1": 63,
    "lbl_Cost_2": 512,
    "lbl_Cost_3": 500,
    "lbl_Country": 45,
    "lbl_Country_1": 55,
    "lbl_Country_2": 505,
    "lbl_Country_3": 495,
    "lbl_Don't have an account?": 364,
    "lbl_errormessage for username and password": 361,
    "lbl_Forgotpassword": 362,
    "lbl_Geo": 44,
    "lbl_Geo_1": 56,
    "lbl_Geo_2": 506,
    "lbl_Geo_3": 493,
    "lbl_Grossmargin%": 48,
    "lbl_Grossmargin%_1": 61,
    "lbl_Grossmargin%_2": 510,
    "lbl_Grossmargin%_3": 498,
    "lbl_Insurance": 12,
    "lbl_Login": 355,
    "lbl_P&L": 51,
    "lbl_P&L_1": 64,
    "lbl_P&L_2": 513,
    "lbl_P&L_3": 501,
    "lbl_Password": 358,
    "lbl_Revenue": 49,
    "lbl_Revenue_1": 62,
    "lbl_Revenue_2": 511,
    "lbl_Revenue_3": 499,
    "lbl_UserName": 14,
    "lbl_UserName_1": 5,
    "lbl-Username": 356,
    "Login": 351,
    "New Project": 365,
    "New Project_1": 365,
    "NextArrow": 57,
    "Offshore #_DataCard1": 382,
    "Offshore #_DataCard1_1": 382,
    "Offshore #_DataCard2": 231,
    "Onsite #_DataCard1": 381,
    "Onsite #_DataCard1_1": 381,
    "Onsite #_DataCard2": 230,
    "Onsite/offshore_DataCard1": 103,
    "Onsite/offshore_DataCard2": 72,
    "P&L %_DataCard1": 113,
    "P&L %_DataCard2": 82,
    "P&L_DataCard1": 112,
    "P&L_DataCard2": 81,
    "Project code_DataCard1": 372,
    "Project code_DataCard1_1": 372,
    "Project code_DataCard2": 221,
    "Project Dashboard Screen": 480,
    "Project end date_DataCard1": 378,
    "Project end date_DataCard1_1": 378,
    "Project end date_DataCard2": 227,
    "Project Manager_DataCard1": 374,
    "Project Manager_DataCard1_1": 374,
    "Project Manager_DataCard2": 69,
    "Project Manager_DataCard3": 223,
    "Project Manager_DataCard4": 100,
    "Project Name_DataCard1": 373,
    "Project Name_DataCard1_1": 373,
    "Project Name_DataCard2": 222,
    "Project Start Date_DataCard1": 377,
    "Project Start Date_DataCard1_1": 377,
    "Project Start Date_DataCard2": 226,
    "Project status_DataCard1": 389,
    "Project status_DataCard1_1": 389,
    "Project status_DataCard2": 240,
    "Quarter_DataCard2": 85,
    "Quarter_DataCard3": 238,
    "Quarter_DataCard4": 116,
    "rct_Header": 10,
    "rct_Header_1": 2,
    "rct_Header_2": 16,
    "rct_Login": 354,
    "rct_Login1": 352,
    "record comments_DataCard1": 99,
    "Record comments_DataCard1": 248,
    "Record status_DataCard1": 247,
    "Record status_DataCard3": 120,
    "Rectangle1": 21,
    "Rectangle2": 25,
    "Revenue Year_DataCard1": 117,
    "Revenue Year_DataCard2": 86,
    "Revenue_DataCard1": 110,
    "Revenue_DataCard2": 79,
    "Risk Status (RAG)_DataCard1": 241,
    "Schedule variance (# days)_DataCard1": 245,
    "Separator": 65,
    "Separator_1": 514,
    "StarVisible1": 394,
    "StarVisible1_1": 394,
    "StarVisible10": 431,
    "StarVisible10_1": 431,
    "StarVisible100": 200,
    "StarVisible101": 204,
    "StarVisible102": 208,
    "StarVisible103": 212,
    "StarVisible104": 129,
    "StarVisible105": 216,
    "StarVisible11": 435,
    "StarVisible11_1": 435,
    "StarVisible12": 439,
    "StarVisible12_1": 439,
    "StarVisible13": 443,
    "StarVisible13_1": 443,
    "StarVisible14": 447,
    "StarVisible14_1": 447,
    "StarVisible15": 451,
    "StarVisible15_1": 451,
    "StarVisible16": 455,
    "StarVisible16_1": 455,
    "StarVisible17": 459,
    "StarVisible17_1": 459,
    "StarVisible18": 463,
    "StarVisible18_1": 463,
    "StarVisible2": 399,
    "StarVisible2_1": 399,
    "StarVisible21": 467,
    "StarVisible21_1": 467,
    "StarVisible22": 471,
    "StarVisible22_1": 471,
    "StarVisible25": 475,
    "StarVisible25_1": 475,
    "StarVisible3": 403,
    "StarVisible3_1": 403,
    "StarVisible31": 479,
    "StarVisible31_1": 479,
    "StarVisible4": 407,
    "StarVisible4_1": 407,
    "StarVisible5": 411,
    "StarVisible5_1": 411,
    "StarVisible56": 254,
    "StarVisible57": 258,
    "StarVisible58": 262,
    "StarVisible59": 266,
    "StarVisible6": 415,
    "StarVisible6_1": 415,
    "StarVisible60": 270,
    "StarVisible61": 274,
    "StarVisible62": 278,
    "StarVisible63": 282,
    "StarVisible64": 286,
    "StarVisible65": 290,
    "StarVisible66": 294,
    "StarVisible67": 298,
    "StarVisible68": 302,
    "StarVisible69": 306,
    "StarVisible7": 419,
    "StarVisible7_1": 419,
    "StarVisible70": 310,
    "StarVisible71": 314,
    "StarVisible72": 318,
    "StarVisible73": 322,
    "StarVisible74": 326,
    "StarVisible75": 330,
    "StarVisible76": 334,
    "StarVisible77": 338,
    "StarVisible78": 342,
    "StarVisible79": 346,
    "StarVisible8": 423,
    "StarVisible8_1": 423,
    "StarVisible80": 350,
    "StarVisible82": 125,
    "StarVisible83": 132,
    "StarVisible84": 136,
    "StarVisible85": 140,
    "StarVisible86": 144,
    "StarVisible87": 148,
    "StarVisible88": 152,
    "StarVisible89": 156,
    "StarVisible9": 427,
    "StarVisible9_1": 427,
    "StarVisible90": 160,
    "StarVisible91": 164,
    "StarVisible92": 168,
    "StarVisible93": 172,
    "StarVisible94": 176,
    "StarVisible95": 180,
    "StarVisible96": 184,
    "StarVisible97": 188,
    "StarVisible98": 192,
    "StarVisible99": 196,
    "Tax %_DataCard1": 108,
    "Tax %_DataCard2": 77,
    "Tax Amount in Usd_DataCard1": 109,
    "Tax Amount in Usd_DataCard2": 78,
    "TextInput1": 35,
    "TextInput1_1": 482,
    "TextInput2": 39,
    "TextInput2_1": 485,
    "TextInput3": 41,
    "TextInput3_1": 488,
    "TextInput3_2": 494,
    "Total #_DataCard1": 383,
    "Total #_DataCard1_1": 383,
    "Total #_DataCard2": 232,
    "Total Cost in USD_DataCard1": 380,
    "Total Cost in USD_DataCard1_1": 380,
    "Total Cost in USD_DataCard2": 229,
    "txt_Password": 359,
    "txt_Username": 357,
    "Type of contract_DataCard1": 388,
    "Type of contract_DataCard1_1": 388,
    "Type of contract_DataCard2": 239,
    "Type of Engagement_DataCard1": 379,
    "Type of Engagement_DataCard1_1": 379,
    "Type of Engagement_DataCard2": 228,
    "Type of project_DataCard1": 390,
    "Type of project_DataCard1_1": 390,
    "Type of project_DataCard2": 243,
    "Upload DM approval email _DataCard1": 246,
    "year_DataCard2": 237
  },
  "ResourcesJsonIndices": {
    "Image-Coforge logo (1)": 1,
    "Image-COFORGE.NS_BIG-6fe17054": 2,
    "Image-SampleImage": 0
  },
  "RuleScreenIdWithoutScreen": {},
  "TemplateVersions": {},
  "VolatileProperties": {
    "AnalysisLoadTime": 4.8828763,
    "ControlCount": {
      "3117ead71d154f21b8f2684993e2a127": 2,
      "4832bbbf1ea84dd6925ae3108c0252ee": 3,
      "attachments": 2,
      "ba4b9730a2a542e9a6d7429ca58b71bc": 1,
      "button": 13,
      "datepicker": 7,
      "dropdown": 13,
      "e20a402af7de411fa32417369e90a871": 1,
      "form": 5,
      "gallery": 2,
      "galleryTemplate": 2,
      "group": 3,
      "icon": 7,
      "image": 6,
      "label": 338,
      "rectangle": 9,
      "screen": 9,
      "text": 83,
      "typedDataCard": 121
    },
    "DeserializationLoadTime": 6.1404772
  },
  "WasLocalDatabaseReferencesEmpty": true
}